{
  "name": "Material Code Dark",
  "type": "dark",
  "colors": {
    "activityBar.activeBorder": "#4285f4",
    "activityBar.background": "#2c2e31",
    "activityBar.border": "#ffffff00",
    "activityBar.dropBackground": "#f34c7e80",
    "activityBar.foreground": "#ffffff",
    "activityBarBadge.background": "#4285f4",
    "activityBarBadge.foreground": "#000000",
    "badge.background": "#3a3c41",
    "badge.foreground": "#ffffff",
    "breadcrumb.activeSelectionForeground": "#4285f4",
    "breadcrumb.background": "#2c2e31",
    "breadcrumb.focusForeground": "#ffffff",
    "breadcrumb.foreground": "#7f8799",
    "breadcrumbPicker.background": "#2c2e31",
    "button.background": "#3a3c41",
    "button.foreground": "#ffffff",
    "debugToolBar.background": "#2c2e31",
    "diffEditor.insertedTextBackground": "#89ddff20",
    "diffEditor.removedTextBackground": "#ff9cac20",
    "dropdown.background": "#2c2e31",
    "dropdown.border": "#ffffff00",
    "editor.background": "#2c2e31",
    "editor.findMatchBackground": "#ffffff",
    "editor.findMatchBorder": "#ffffff",
    "editor.findMatchHighlightBackground": "#3a3c41",
    "editor.findMatchHighlightBorder": "#ffffff00",
    "editor.findRangeHighlightBackground": "#3ddc8420",
    "editor.foreground": "#ffffff",
    "editor.lineHighlightBackground": "#26282a",
    "editor.lineHighlightBorder": "#ffffff00",
    "editor.rangeHighlightBackground": "#ffffff0d",
    "editor.selectionBackground": "#7f879930",
    "editor.selectionHighlightBackground": "#f34c7e20",
    "editor.wordHighlightBackground": "#ff9cac30",
    "editor.wordHighlightStrongBackground": "#c3e88d30",
    "editorBracketMatch.background": "#2c2e31",
    "editorBracketMatch.border": "#ffcc0050",
    "editorCursor.foreground": "#00f0a0",
    "editorError.foreground": "#f34c7e70",
    "editorGroup.dropBackground": "#5495ff90",
    "editorGroupHeader.tabsBackground": "#2c2e31",
    "editorGroup.border": "#34363a",
    "editorGroup.focusedEmptyBorder": "#f34c7e",
    "editorGutter.addedBackground": "#c3e88d60",
    "editorGutter.deletedBackground": "#f34c7e60",
    "editorGutter.modifiedBackground": "#82aaff60",
    "editorHoverWidget.background": "#2c2e31",
    "editorHoverWidget.border": "#ffffff10",
    "editorIndentGuide.activeBackground": "#424242",
    "editorIndentGuide.background": "#42424270",
    "editorInfo.foreground": "#82aaff70",
    "editorLineNumber.activeForeground": "#7f8799",
    "editorLineNumber.foreground": "#424242",
    "editorLink.activeForeground": "#ffffff",
    "editorMarkerNavigation.background": "#ffffff05",
    "editorOverviewRuler.border": "#2c2e31",
    "editorOverviewRuler.errorForeground": "#f34c7e40",
    "editorOverviewRuler.findMatchForeground": "#4285f4",
    "editorOverviewRuler.infoForeground": "#82aaff40",
    "editorOverviewRuler.warningForeground": "#ffcc5e40",
    "editorRuler.foreground": "#424242",
    "editorSuggestWidget.background": "#2c2e31",
    "editorSuggestWidget.border": "#ffffff00",
    "editorSuggestWidget.foreground": "#ffffff",
    "editorSuggestWidget.highlightForeground": "#00f0a0",
    "editorSuggestWidget.selectedBackground": "#1f2124",
    "editorWarning.foreground": "#ffcc5e",
    "editorWhitespace.foreground": "#7f8799",
    "editorWidget.background": "#2c2e31",
    "editorWidget.border": "#4285f4",
    "editorWidget.resizeBorder": "#4285f4",
    "extensionBadge.remoteForeground": "#ffffff",
    "extensionButton.prominentBackground": "#c3e88d90",
    "extensionButton.prominentForeground": "#000000",
    "extensionButton.prominentHoverBackground": "#c3e88d",
    "focusBorder": "#ffffff00",
    "foreground": "#ffffff",
    "input.background": "#2c2e31",
    "input.border": "#3a3c41",
    "input.foreground": "#ffffff",
    "input.placeholderForeground": "#7f8799",
    "inputOption.activeBackground": "#ffffff30",
    "inputOption.activeBorder": "#ffffff30",
    "inputValidation.errorBorder": "#f34c7e50",
    "inputValidation.infoBorder": "#82aaff50",
    "inputValidation.warningBorder": "#ffcc5e50",
    "list.activeSelectionBackground": "#2c2e31",
    "list.activeSelectionForeground": "#4285f4",
    "list.dropBackground": "#f34c7e80",
    "list.focusBackground": "#ffffff20",
    "list.focusForeground": "#ffffff",
    "list.highlightForeground": "#4285f4",
    "list.hoverBackground": "#27282b",
    "list.hoverForeground": "#ffffff",
    "list.inactiveSelectionBackground": "#27282b",
    "list.inactiveSelectionForeground": "#ffffff",
    "listFilterWidget.background": "#00000030",
    "listFilterWidget.noMatchesOutline": "#00000030",
    "listFilterWidget.outline": "#00000030",
    "menu.background": "#2c2e31",
    "menu.foreground": "#c5cbd9",
    "menu.selectionBackground": "#3a3c41",
    "menu.selectionBorder": "#ffffff00",
    "menu.selectionForeground": "#ffffff",
    "menu.separatorBackground": "#ffffff",
    "menubar.selectionBackground": "#3a3c41",
    "menubar.selectionBorder": "#ffffff00",
    "menubar.selectionForeground": "#ffffff",
    "notificationLink.foreground": "#4285f4",
    "notifications.background": "#2c2e31",
    "notifications.foreground": "#ffffff",
    "panel.background": "#2c2e31",
    "panel.border": "#ffffff00",
    "panel.dropBackground": "#ffffff",
    "panelTitle.activeBorder": "#4285f4",
    "panelTitle.activeForeground": "#ffffff",
    "panelTitle.inactiveForeground": "#ffffff",
    "peekView.border": "#00000030",
    "peekViewEditor.background": "#ffffff05",
    "peekViewEditor.matchHighlightBackground": "#7f879950",
    "peekViewEditorGutter.background": "#ffffff05",
    "peekViewResult.background": "#ffffff05",
    "peekViewResult.matchHighlightBackground": "#7f879950",
    "peekViewResult.selectionBackground": "#7f879970",
    "peekViewTitle.background": "#ffffff05",
    "peekViewTitleDescription.foreground": "#ffffff60",
    "pickerGroup.border": "#ffffff1a",
    "pickerGroup.foreground": "#4285f4",
    "progressBar.background": "#4285f4",
    "scrollbar.shadow": "#ffffff00",
    "scrollbarSlider.activeBackground": "#7f8799",
    "scrollbarSlider.background": "#34363a",
    "scrollbarSlider.hoverBackground": "#3a3c41",
    "selection.background": "#4285f4",
    "settings.checkboxBackground": "#ffffff00",
    "settings.checkboxForeground": "#4285f4",
    "settings.dropdownBackground": "#2c2e31",
    "settings.dropdownForeground": "#ffffff",
    "settings.headerForeground": "#4285f4",
    "settings.modifiedItemIndicator": "#4285f4",
    "settings.numberInputBackground": "#ffffff00",
    "settings.numberInputForeground": "#ffffff",
    "settings.textInputBackground": "#ffffff00",
    "settings.textInputForeground": "#ffffff",
    "sideBar.background": "#2c2e31",
    "sideBar.border": "#ffffff00",
    "sideBar.foreground": "#7f8799",
    "sideBarSectionHeader.background": "#2c2e31",
    "sideBarSectionHeader.border": "#ffffff00",
    "sideBarTitle.foreground": "#7f8799",
    "statusBar.background": "#2c2e31",
    "statusBar.border": "#ffffff00",
    "statusBar.debuggingBackground": "#c792ea",
    "statusBar.debuggingForeground": "#ffffff",
    "statusBar.foreground": "#7f8799",
    "statusBar.noFolderBackground": "#2c2e31",
    "statusBarItem.activeBackground": "#f34c7e80",
    "statusBarItem.hoverBackground": "#54545420",
    "statusBarItem.remoteBackground": "#4285f4",
    "statusBarItem.remoteForeground": "#000000",
    "tab.activeBackground": "#2c2e31",
    "tab.inactiveBackground": "#2c2e31",
    "tab.hoverBackground": "#363940",
    "tab.activeForeground": "#ffffff",
    "tab.inactiveForeground": "#808796",
    "tab.activeBorder": "#5495ff",
    "tab.border": "#ffffff00",
    "terminal.ansiBlack": "#000000",
    "terminal.ansiBlue": "#4285f4",
    "terminal.ansiBrightBlack": "#545454",
    "terminal.ansiBrightBlue": "#609dff",
    "terminal.ansiBrightCyan": "#89ddff",
    "terminal.ansiBrightGreen": "#c3e88d",
    "terminal.ansiBrightMagenta": "#c792ea",
    "terminal.ansiBrightRed": "#f34c7e",
    "terminal.ansiBrightWhite": "#ffffff",
    "terminal.ansiBrightYellow": "#ffcc5e",
    "terminal.ansiCyan": "#89ddff",
    "terminal.ansiGreen": "#c3e88d",
    "terminal.ansiMagenta": "#c792ea",
    "terminal.ansiRed": "#f34c7e",
    "terminal.ansiWhite": "#ffffff",
    "terminal.ansiYellow": "#ffcc5e",
    "terminalCursor.background": "#ffffff00",
    "terminalCursor.foreground": "#00f0a0",
    "textLink.activeForeground": "#ffffff",
    "textLink.foreground": "#4285f4",
    "titleBar.activeBackground": "#2c2e31",
    "titleBar.activeForeground": "#c5cbd9",
    "titleBar.border": "#ffffff00",
    "titleBar.inactiveBackground": "#2c2e31",
    "titleBar.inactiveForeground": "#7f8799",
    "tree.indentGuidesStroke": "#424242",
    "widget.shadow": "#232529"
  },
  "tokenColors": [
    {
      "scope": ["comment", "punctuation.definition.comment"],
      "settings": {
        "foreground": "#6e8ea0"
      }
    },
    {
      "scope": [
        "",
        "keyword",
        "punctuation",
        "entity.name.function",
        "support.constant",
        "constant.other.color",
        "constant.numeric.css",
        "keyword.other.unit"
      ],
      "settings": {
        "foreground": "#b0cad6"
      }
    },
    {
      "scope": [
        "string",
        "entity.other.attribute-name.id",
        "meta.attribute-selector.scss",
        "markup.inline.raw.string.markdown",
        "markup.fenced_code.block.markdown",
        "punctuation.definition.raw.markdown",
        "punctuation.definition.markdown"
      ],
      "settings": {
        "foreground": "#00eb9c"
      }
    },
    {
      "scope": [
        "storage.type",
        "keyword.control",
        "entity.name.tag",
        "punctuation.definition.tag.begin.html",
        "punctuation.definition.tag.end.html",
        "support.type.property-name.json",
        "string.other.link.title.markdown",
        "string.other.link.description.markdown"
      ],
      "settings": {
        "foreground": "#ff60ff"
      }
    },
    {
      "scope": [
        "variable",
        "support.function",
        "entity.other.attribute-name",
        "meta.link.inline.markdown",
        "meta.separator.markdown",
        "punctuation.definition.quote.begin.markdown"
      ],
      "settings": {
        "foreground": "#0e9aff"
      }
    },
    {
      "scope": [
        "variable.parameter",
        "variable.language",
        "variable.other.property",
        "variable.other.constant.property.js",
        "variable.other.constant.object.property.js",
        "support.type.property-name.css",
        "string.json.comments",
        "markup.heading.markdown",
        "punctuation.definition.heading.markdown"
      ],
      "settings": {
        "foreground": "#f84d86"
      }
    },
    {
      "scope": [
        "support.class",
        "constant.numeric",
        "constant.language",
        "entity.other.attribute-name.class",
        "punctuation.definition.list.begin.markdown"
      ],
      "settings": {
        "foreground": "#f8c558"
      }
    }
  ]
}
